LICENSE.txt
MANIFEST.in
README.rst
setup.cfg
setup.py
tests/__init__.py
tests/test_widgets.py
tw2/__init__.py
tw2.forms.egg-info/PKG-INFO
tw2.forms.egg-info/SOURCES.txt
tw2.forms.egg-info/dependency_links.txt
tw2.forms.egg-info/entry_points.txt
tw2.forms.egg-info/namespace_packages.txt
tw2.forms.egg-info/not-zip-safe
tw2.forms.egg-info/requires.txt
tw2.forms.egg-info/top_level.txt
tw2/forms/__init__.py
tw2/forms/calendars.py
tw2/forms/datagrid.py
tw2/forms/mashups.py
tw2/forms/samples.py
tw2/forms/widgets.py
tw2/forms/static/dialog-warning.png
tw2/forms/static/edit-undo.png
tw2/forms/static/forms.css
tw2/forms/static/calendar/calendar-blue.css
tw2/forms/static/calendar/calendar-blue2.css
tw2/forms/static/calendar/calendar-brown.css
tw2/forms/static/calendar/calendar-green.css
tw2/forms/static/calendar/calendar-setup.js
tw2/forms/static/calendar/calendar-system.css
tw2/forms/static/calendar/calendar-tas.css
tw2/forms/static/calendar/calendar-win2k-1.css
tw2/forms/static/calendar/calendar-win2k-2.css
tw2/forms/static/calendar/calendar-win2k-cold-1.css
tw2/forms/static/calendar/calendar-win2k-cold-2.css
tw2/forms/static/calendar/calendar.js
tw2/forms/static/calendar/menuarrow.gif
tw2/forms/static/calendar/menuarrow2.gif
tw2/forms/static/calendar/lang/calendar-af.js
tw2/forms/static/calendar/lang/calendar-bg-cp1251.js
tw2/forms/static/calendar/lang/calendar-bg.js
tw2/forms/static/calendar/lang/calendar-ca.js
tw2/forms/static/calendar/lang/calendar-cs-cp1250.js
tw2/forms/static/calendar/lang/calendar-cs.js
tw2/forms/static/calendar/lang/calendar-da.js
tw2/forms/static/calendar/lang/calendar-de.js
tw2/forms/static/calendar/lang/calendar-de_at.js
tw2/forms/static/calendar/lang/calendar-de_de.js
tw2/forms/static/calendar/lang/calendar-el.js
tw2/forms/static/calendar/lang/calendar-en.js
tw2/forms/static/calendar/lang/calendar-es.js
tw2/forms/static/calendar/lang/calendar-fi.js
tw2/forms/static/calendar/lang/calendar-fr.js
tw2/forms/static/calendar/lang/calendar-he.js
tw2/forms/static/calendar/lang/calendar-hr.js
tw2/forms/static/calendar/lang/calendar-hu-cp1252.js
tw2/forms/static/calendar/lang/calendar-hu.js
tw2/forms/static/calendar/lang/calendar-it.js
tw2/forms/static/calendar/lang/calendar-ja.js
