Metadata-Version: 2.1
Name: tw2.forms
Version: 2.2.6
Summary: The basic form widgets for ToscaWidgets 2, a web widget toolkit.
Home-page: http://toscawidgets.org/
Author: Paul Johnston, Christopher Perkins, Alberto Valverde Gonzalez & contributors
Author-email: toscawidgets-discuss@googlegroups.com
License: MIT
Download-URL: https://pypi.python.org/pypi/tw2.forms/
Keywords: toscawidgets.widgets
Platform: UNKNOWN
Classifier: Development Status :: 5 - Production/Stable
Classifier: Environment :: Web Environment
Classifier: Environment :: Web Environment :: ToscaWidgets
Classifier: Topic :: Software Development :: Libraries :: Python Modules
Classifier: Topic :: Software Development :: Widget Sets
Classifier: Intended Audience :: Developers
Classifier: Operating System :: OS Independent
Classifier: Programming Language :: Python
Classifier: License :: OSI Approved :: MIT License
Provides-Extra: genshi
Provides-Extra: jinja
Provides-Extra: kajiki
Provides-Extra: mako
Provides-Extra: test
Provides-Extra: tests
